yggdata/__init__.py
yggdata/inputs.py
yggdata/yggdrasil.py
yggdata-0.1.0.dist-info/licenses/LICENSE
yggdata-0.1.0.dist-info/METADATA
yggdata-0.1.0.dist-info/WHEEL
yggdata-0.1.0.dist-info/top_level.txt
yggdata-0.1.0.dist-info/RECORD
