Metadata-Version: 2.4
Name: yggdata
Version: 0.1.0
Summary: A flexible tree-like data structure for Python and some input features
Author-email: Cedric Sascha Wagner <cedric.sascha.wagner@outlook.de>
License: MIT
Project-URL: Homepage, https://github.com/LilLordCedric/YggData
Project-URL: Repository, https://github.com/LilLordCedric/YggData
Classifier: Programming Language :: Python :: 3
Classifier: License :: OSI Approved :: MIT License
Classifier: Operating System :: OS Independent
Requires-Python: >=3.6
License-File: LICENSE
Requires-Dist: pandas>=2.0.0
Dynamic: license-file
